{"examples.md":"ykED_Nwf","howto_decompose.md":"D_miZcAy","howto_defineorder.md":"BnvcLd4a","howto_index.md":"Bv-X7Uw2","howto_pip.md":"DFqjO01m","howto_reduction.md":"CHyhAXUE","howto_resfield.md":"BqSttwMx","index.md":"CAtmgK3l","manual_abelian_elements.md":"ClrZGX0i","manual_abelian_introduction.md":"CV_EutCA","manual_abelian_maps.md":"JVfzry-J","manual_abelian_structural.md":"ZF3v9L3V","manual_algebras_basics.md":"DiE3auM6","manual_algebras_groupalgebras.md":"DwV409GJ","manual_algebras_ideals.md":"CbfRbkmV","manual_algebras_intro.md":"CPDAvCTe","manual_algebras_quaternion.md":"Dcc3Qa_L","manual_algebras_structureconstant.md":"C91BpaqA","manual_developer_documentation.md":"HPJ1SzKI","manual_developer_test.md":"B5zYz5a8","manual_elliptic_curves_basics.md":"DAur3JOk","manual_elliptic_curves_finite_fields.md":"BGlHvQ-I","manual_elliptic_curves_intro.md":"MkLMEWzf","manual_elliptic_curves_number_fields.md":"Bu5x9vGI","manual_index.md":"DuZAamNw","manual_misc_conjugacy.md":"BlXfm6lP","manual_misc_facelem.md":"JNckpNbH","manual_misc_mset.md":"y5PPKrYb","manual_misc_pmat.md":"BNN98vuw","manual_misc_sparse.md":"B7mD_URP","manual_number_fields_class_fields.md":"C5vOi91d","manual_number_fields_complex_embeddings.md":"DOPJZ0D3","manual_number_fields_conventions.md":"_xF6IYkW","manual_number_fields_elements.md":"C0KGTZxk","manual_number_fields_fields.md":"BXU71LOs","manual_number_fields_internal.md":"DcMYTfJf","manual_number_fields_intro.md":"D3Rsj81g","manual_orders_elements.md":"BT7ZQRDk","manual_orders_frac_ideals.md":"vGBxYLB1","manual_orders_ideals.md":"C2q3SEcD","manual_orders_introduction.md":"CcHz8DYZ","manual_orders_orders.md":"Cv-6cpgh","manual_quad_forms_basics.md":"Yy4_EZlv","manual_quad_forms_discriminant_group.md":"CV-xBzhM","manual_quad_forms_genusherm.md":"DFfvUJt9","manual_quad_forms_integer_lattices.md":"CkLo8r1S","manual_quad_forms_introduction.md":"BDXTm2dn","manual_quad_forms_lattices.md":"DoR1N2lH","manual_quad_forms_zgenera.md":"DrP4a9_r","references.md":"nXVEhlGx","start_index.md":"DvjY3rM6","tutorials_index.md":"ye61LqaI","tutorials_quaternion.md":"CiFXZOir"}
