{"examples.md":"CNUbGP9o","howto_index.md":"Bd0lMHlZ","howto_reduction.md":"NDHU1E_R","index.md":"Db-BCFbs","manual_abelian_elements.md":"BnUfiQaK","manual_abelian_introduction.md":"BlxzQozD","manual_abelian_maps.md":"qZRJvD1_","manual_abelian_structural.md":"BC3IuDD1","manual_algebras_basics.md":"C-kyVNQb","manual_algebras_groupalgebras.md":"L-lyHxLh","manual_algebras_intro.md":"CrqyPhyz","manual_algebras_structureconstant.md":"BkaPqDdy","manual_developer_documentation.md":"BYiLFYxc","manual_developer_test.md":"DxWycPiT","manual_elliptic_curves_basics.md":"RNqClRhL","manual_elliptic_curves_finite_fields.md":"DISLKLQK","manual_elliptic_curves_intro.md":"Hm8GEm1w","manual_elliptic_curves_number_fields.md":"BgQceBRJ","manual_index.md":"DE87lFy5","manual_misc_conjugacy.md":"B8k3XOv5","manual_misc_facelem.md":"DJYjtvXm","manual_misc_mset.md":"Berud3xF","manual_misc_pmat.md":"BtlwJFvU","manual_misc_sparse.md":"GMPhupDk","manual_number_fields_class_fields.md":"DGpCh7r7","manual_number_fields_complex_embeddings.md":"DbGbccr6","manual_number_fields_conventions.md":"DjGCEOH1","manual_number_fields_elements.md":"Bs3tfGWV","manual_number_fields_fields.md":"Bl3xuQtZ","manual_number_fields_internal.md":"BLn9zMhx","manual_number_fields_intro.md":"Depyowen","manual_orders_elements.md":"CW624TEk","manual_orders_frac_ideals.md":"Bf1wbXcR","manual_orders_ideals.md":"BtivhNND","manual_orders_introduction.md":"CM7Kf-h9","manual_orders_orders.md":"9LfGaql3","manual_quad_forms_basics.md":"Cv28XOYS","manual_quad_forms_discriminant_group.md":"DJYx0k_Q","manual_quad_forms_genusherm.md":"CqJK7BYM","manual_quad_forms_integer_lattices.md":"CRBIhcVB","manual_quad_forms_introduction.md":"De_4nEby","manual_quad_forms_lattices.md":"DDuoN6eb","manual_quad_forms_zgenera.md":"CxOQoOOL","references.md":"BPx1bagT","start_index.md":"CxGuc9pG","tutorials_index.md":"DAH4euSa"}
